eye_tracking_collector/assets/encsa.txt
eye_tracking_collector/cli.py
eye_tracking_collector/collect.py
eye_tracking_collector/upload/google/__init__.py
eye_tracking_collector/upload/google/key.py
eye_tracking_collector/upload/google/storage.py
eye_tracking_collector/upload/kaggle.py
eye_tracking_collector-0.0.4.dist-info/METADATA
eye_tracking_collector-0.0.4.dist-info/WHEEL
eye_tracking_collector-0.0.4.dist-info/entry_points.txt
eye_tracking_collector-0.0.4.dist-info/RECORD
