Metadata-Version: 2.3
Name: eye-tracking-collector
Version: 0.0.4
Summary: Tool for eye-tracking data collection
Author: Popis
Author-email: piotrpopis98@icloud.com
Requires-Python: >=3.12,<4.0.0
Classifier: Programming Language :: Python :: 3
Classifier: Programming Language :: Python :: 3.12
Classifier: Programming Language :: Python :: 3.13
Requires-Dist: cryptography (>=44.0.0,<45.0.0)
Requires-Dist: google-api-python-client (>=2.156.0,<3.0.0)
Requires-Dist: mediapipe (>=0.10.20)
Requires-Dist: opencv-python (>=4.10.0.84)
Requires-Dist: pyqt6 (>=6.8.0,<7.0.0)
Requires-Dist: screeninfo (>=0.8.1,<0.9.0)
Requires-Dist: tabulate (>=0.9.0,<0.10.0)
Requires-Dist: typer (>=0.15.1,<0.16.0)
